{
	"configurations" : 
	[
		{
			"directories" : 
			[
				{
					"build" : ".",
					"hasInstallRule" : true,
					"jsonFile" : "directory-.-Debug-366e8b362ada25565299.json",
					"minimumCMakeVersion" : 
					{
						"string" : "3.16"
					},
					"projectIndex" : 0,
					"source" : ".",
					"targetIndexes" : 
					[
						0,
						1
					]
				}
			],
			"name" : "Debug",
			"projects" : 
			[
				{
					"directoryIndexes" : 
					[
						0
					],
					"name" : "move",
					"targetIndexes" : 
					[
						0,
						1
					]
				}
			],
			"targets" : 
			[
				{
					"directoryIndex" : 0,
					"id" : "move::@6890427a1f51a3e7e1df",
					"jsonFile" : "target-move-Debug-b6177adb03d5fe929a7c.json",
					"name" : "move",
					"projectIndex" : 0
				},
				{
					"directoryIndex" : 0,
					"id" : "move_autogen::@6890427a1f51a3e7e1df",
					"jsonFile" : "target-move_autogen-Debug-8dc657b3104895f21508.json",
					"name" : "move_autogen",
					"projectIndex" : 0
				}
			]
		}
	],
	"kind" : "codemodel",
	"paths" : 
	{
		"build" : "/home/repetitor/_QtProjects/move/bin",
		"source" : "/home/repetitor/_QtProjects/move"
	},
	"version" : 
	{
		"major" : 2,
		"minor" : 4
	}
}
